odoo10_addon_partner_risk_insurance-10.0.1.0.0-py2.7-nspkg.pth
odoo/addons/partner_risk_insurance/README.rst
odoo/addons/partner_risk_insurance/__init__.py
odoo/addons/partner_risk_insurance/__manifest__.py
odoo/addons/partner_risk_insurance/i18n/ca.po
odoo/addons/partner_risk_insurance/i18n/es.po
odoo/addons/partner_risk_insurance/i18n/pt.po
odoo/addons/partner_risk_insurance/i18n/pt_BR.po
odoo/addons/partner_risk_insurance/i18n/sl.po
odoo/addons/partner_risk_insurance/models/__init__.py
odoo/addons/partner_risk_insurance/models/partner.py
odoo/addons/partner_risk_insurance/tests/__init__.py
odoo/addons/partner_risk_insurance/tests/test_partner_risk_insurance.py
odoo/addons/partner_risk_insurance/views/res_partner_view.xml
odoo10_addon_partner_risk_insurance-10.0.1.0.0.dist-info/DESCRIPTION.rst
odoo10_addon_partner_risk_insurance-10.0.1.0.0.dist-info/METADATA
odoo10_addon_partner_risk_insurance-10.0.1.0.0.dist-info/RECORD
odoo10_addon_partner_risk_insurance-10.0.1.0.0.dist-info/WHEEL
odoo10_addon_partner_risk_insurance-10.0.1.0.0.dist-info/metadata.json
odoo10_addon_partner_risk_insurance-10.0.1.0.0.dist-info/namespace_packages.txt
odoo10_addon_partner_risk_insurance-10.0.1.0.0.dist-info/top_level.txt
